{"Celta Vigo ": {"11": {"position": "nsFW", "name": "Iago Aspas"}, "10": {"position": "nsFW", "name": "Bongonda"}, "1": {"position": "nsXX", "name": "Sergio Alvarez"}, "3": {"position": "nsDF", "name": "Hugo Mallo"}, "2": {"position": "nsDF", "name": "Jonny"}, "5": {"position": "nsDF", "name": "Planas"}, "4": {"position": "nsDF", "name": "Cabral"}, "7": {"position": "nsAM", "name": "HernAndez"}, "6": {"position": "nsDM", "name": "Radoja"}, "9": {"position": "nsFW", "name": "Orellana"}, "8": {"position": "nsFW", "name": "Beauvue"}}, "Las Palmas": {"11": {"position": "nsFW", "name": "Willian JosA"}, "10": {"position": "nsFW", "name": "Viera"}, "1": {"position": "nsXX", "name": "Varas"}, "3": {"position": "nsDF", "name": "David GarcAa"}, "2": {"position": "nsDF", "name": "David SimA3n"}, "5": {"position": "nsDF", "name": "Dani Castellano"}, "4": {"position": "nsDF", "name": "Aythami"}, "7": {"position": "nsMF", "name": "Roque Mesa"}, "6": {"position": "nsMF", "name": "Montoro"}, "9": {"position": "nsAM", "name": "Tana"}, "8": {"position": "nsMF", "name": "Mubarak"}}}