{"Granada CF ": {"11": {"position": "nsFW", "name": "El Arabi"}, "10": {"position": "nsFW", "name": "PeAaranda"}, "1": {"position": "nsXX", "name": "FernAndez"}, "3": {"position": "nsDF", "name": "Babin"}, "2": {"position": "nsDF", "name": "Miguel Lopes"}, "5": {"position": "nsDF", "name": "Biraghi"}, "4": {"position": "nsDF", "name": "Ricardo Costa"}, "7": {"position": "nsMF", "name": "RubAn PArez"}, "6": {"position": "nsFW", "name": "Rochina"}, "9": {"position": "nsFW", "name": "Isaac"}, "8": {"position": "nsMF", "name": "Doucoure"}}, "Real Betis": {"11": {"position": "nsFW", "name": "Castro"}, "10": {"position": "nsMF", "name": "Alvaro Cejudo"}, "1": {"position": "nsXX", "name": "AdAn"}, "3": {"position": "nsDF", "name": "Pezzella"}, "2": {"position": "nsDF", "name": "Montoya"}, "5": {"position": "nsMF", "name": "Vargas"}, "4": {"position": "nsDF", "name": "Bruno"}, "7": {"position": "nsMF", "name": "Dani Ceballos"}, "6": {"position": "nsDM", "name": "N Diaye"}, "9": {"position": "nsMF", "name": "FabiAn"}, "8": {"position": "nsAM", "name": "Musonda"}}}