{"Sevilla": {"11": {"position": "nsFW", "name": "Gameiro"}, "10": {"position": "nsMF", "name": "Krohn-Dehli"}, "1": {"position": "nsXX", "name": "Sergio Rico"}, "3": {"position": "nsDF", "name": "Andreolli"}, "2": {"position": "nsDF", "name": "Coke"}, "5": {"position": "nsDF", "name": "Tremoulinas"}, "4": {"position": "nsDF", "name": "Kolodzieczak"}, "7": {"position": "nsDM", "name": "Krychowiak"}, "6": {"position": "nsDM", "name": "N Zonzi"}, "9": {"position": "nsMF", "name": "Iborra"}, "8": {"position": "nsMF", "name": "Vitolo"}}, "Barcelona ": {"11": {"position": "nsFW", "name": "Neymar"}, "10": {"position": "nsFW", "name": "SuArez"}, "1": {"position": "nsXX", "name": "Bravo"}, "3": {"position": "nsDF", "name": "PiquA"}, "2": {"position": "nsMF", "name": "Sergi Roberto"}, "5": {"position": "nsDF", "name": "Jordi Alba"}, "4": {"position": "nsDF", "name": "Mathieu"}, "7": {"position": "nsDM", "name": "Mascherano"}, "6": {"position": "nsMF", "name": "RakitiA"}, "9": {"position": "nsFW", "name": "Munir"}, "8": {"position": "nsDM", "name": "Busquets"}}}