{"Valencia": {"11": {"position": "nsMF", "name": "Piatti"}, "10": {"position": "nsFW", "name": "AlcAcer"}, "1": {"position": "nsXX", "name": "Domenech"}, "3": {"position": "nsDF", "name": "Mustafi"}, "2": {"position": "nsDF", "name": "Barragan"}, "5": {"position": "nsDF", "name": "GayA"}, "4": {"position": "nsDF", "name": "Abdennour"}, "7": {"position": "nsAM", "name": "Parejo"}, "6": {"position": "nsMF", "name": "AndrA Gomes"}, "9": {"position": "nsDF", "name": "JoAo Cancelo"}, "8": {"position": "nsDM", "name": "Danilo"}}, "Getafe ": {"11": {"position": "nsFW", "name": "A AepoviA"}, "10": {"position": "nsMF", "name": "Lafita"}, "1": {"position": "nsXX", "name": "Guaita"}, "3": {"position": "nsDF", "name": "Cala"}, "2": {"position": "nsDF", "name": "SuArez"}, "5": {"position": "nsDF", "name": "Roberto Lago"}, "4": {"position": "nsDF", "name": "Alexis Ruano"}, "7": {"position": "nsDM", "name": "Rodriguez"}, "6": {"position": "nsMF", "name": "Sarabia"}, "9": {"position": "nsAM", "name": "VActor RodrAguez"}, "8": {"position": "nsMF", "name": "Lacen"}}}