{"Real Sociedad ": {"11": {"position": "nsFW", "name": "Bruma"}, "10": {"position": "nsFW", "name": "Jonathas"}, "1": {"position": "nsXX", "name": "Rulli"}, "3": {"position": "nsDF", "name": "Elustondo"}, "2": {"position": "nsDF", "name": "ZaldA1a"}, "5": {"position": "nsDF", "name": "Litri"}, "4": {"position": "nsDF", "name": "IAigo MartAnez"}, "7": {"position": "nsDM", "name": "Bergara"}, "6": {"position": "nsMF", "name": "Prieto"}, "9": {"position": "nsFW", "name": "Vela"}, "8": {"position": "nsDM", "name": "Illarra"}}, "Sporting GijA3n": {"11": {"position": "nsFW", "name": "Sanabria"}, "10": {"position": "nsMF", "name": "Jony"}, "1": {"position": "nsXX", "name": "CuAllar"}, "3": {"position": "nsDF", "name": "Luis HernAndez"}, "2": {"position": "nsDF", "name": "Lora"}, "5": {"position": "nsFW", "name": "Isma LA3pez"}, "4": {"position": "nsDF", "name": "MerA"}, "7": {"position": "nsMF", "name": "AA t-Atmane"}, "6": {"position": "nsMF", "name": "Alvarez"}, "9": {"position": "nsAM", "name": "Dani NA Di"}, "8": {"position": "nsMF", "name": "Carmona B"}}}