{"Villarreal": {"11": {"position": "nsFW", "name": "Soldado"}, "10": {"position": "nsFW", "name": "AdriAn"}, "1": {"position": "nsXX", "name": "ArAola"}, "3": {"position": "nsDF", "name": "Bonera"}, "2": {"position": "nsDF", "name": "Mario Gaspar"}, "5": {"position": "nsDF", "name": "AdriAn MarAn"}, "4": {"position": "nsDF", "name": "Victor Ruiz"}, "7": {"position": "nsMF", "name": "Pina"}, "6": {"position": "nsFW", "name": "Castillejo"}, "9": {"position": "nsAM", "name": "SuArez"}, "8": {"position": "nsDM", "name": "Bruno Soriano"}}, "Las Palmas ": {"11": {"position": "nsFW", "name": "Willian JosA"}, "10": {"position": "nsFW", "name": "El Zhar"}, "1": {"position": "nsXX", "name": "Varas"}, "3": {"position": "nsDF", "name": "Lemos"}, "2": {"position": "nsDF", "name": "David GarcAa"}, "5": {"position": "nsDF", "name": "Garrido"}, "4": {"position": "nsDF", "name": "Bigas"}, "7": {"position": "nsMF", "name": "Momo"}, "6": {"position": "nsMF", "name": "Montoro"}, "9": {"position": "nsFW", "name": "Viera"}, "8": {"position": "nsMF", "name": "Nili"}}}