{"15743": {"rating": "57", "abilities": {"pas": "56", "dri": "56", "phy": "57", "pac": "48", "deff": "56", "sho": "41"}, "Skill-Moves": "2", "Defensive-Workrate": "Med", "club": "heracles-almelo", "age": "21", "Attack-Workrate": "Med", "nation": "19", "potential": "64", "Weak-Foot": "None", "position": "CDM", "heigh": "180", "id": "15743", "name": "rick-hemmink"}, "707": {"rating": "64", "abilities": {"pas": "66", "dri": "64", "phy": "64", "pac": "64", "deff": "54", "sho": "65"}, "Skill-Moves": "1", "Defensive-Workrate": "Med", "club": "heracles-almelo", "age": "31", "Attack-Workrate": "Med", "nation": "28", "potential": "64", "Weak-Foot": "None", "position": "GK", "heigh": "191", "id": "707", "name": "bram-castro"}, "10676": {"rating": "63", "abilities": {"pas": "61", "dri": "68", "phy": "54", "pac": "69", "deff": "58", "sho": "41"}, "Skill-Moves": "2", "Defensive-Workrate": "Med", "club": "heracles-almelo", "age": "21", "Attack-Workrate": "Low", "nation": "19", "potential": "72", "Weak-Foot": "None", "position": "CM", "heigh": "172", "id": "10676", "name": "joey-pelupessy"}, "13918": {"rating": "70", "abilities": {"pas": "71", "dri": "77", "phy": "53", "pac": "71", "deff": "35", "sho": "61"}, "Skill-Moves": "4", "Defensive-Workrate": "Low", "club": "heracles-almelo", "age": "22", "Attack-Workrate": "Med", "nation": "19", "potential": "76", "Weak-Foot": "None", "position": "CAM", "heigh": "173", "id": "13918", "name": "illiass-bel-hassani"}, "13320": {"rating": "57", "abilities": {"pas": "56", "dri": "58", "phy": "51", "pac": "66", "deff": "56", "sho": "46"}, "Skill-Moves": "2", "Defensive-Workrate": "Med", "club": "heracles-almelo", "age": "21", "Attack-Workrate": "Med", "nation": "19", "potential": "63", "Weak-Foot": "None", "position": "CDM", "heigh": "175", "id": "13320", "name": "daan-rienstra"}, "4613": {"rating": "61", "abilities": {"pas": "57", "dri": "65", "phy": "64", "pac": "74", "deff": "61", "sho": "51"}, "Skill-Moves": "2", "Defensive-Workrate": "Med", "club": "heracles-almelo", "age": "31", "Attack-Workrate": "Med", "nation": "13", "potential": "61", "Weak-Foot": "None", "position": "LW", "heigh": "174", "id": "4613", "name": "dragan-paljic"}, "174": {"rating": "67", "abilities": {"pas": "70", "dri": "68", "phy": "55", "pac": "43", "deff": "51", "sho": "67"}, "Skill-Moves": "3", "Defensive-Workrate": "Med", "club": "heracles-almelo", "age": "33", "Attack-Workrate": "Med", "nation": "13", "potential": "67", "Weak-Foot": "None", "position": "CM", "heigh": "176", "id": "174", "name": "simon-cziommer"}, "6884": {"rating": "66", "abilities": {"pas": "64", "dri": "71", "phy": "56", "pac": "65", "deff": "33", "sho": "62"}, "Skill-Moves": "3", "Defensive-Workrate": "Med", "club": "heracles-almelo", "age": "24", "Attack-Workrate": "Med", "nation": "51", "potential": "72", "Weak-Foot": "None", "position": "CAM", "heigh": "180", "id": "6884", "name": "dario-vujicevic"}, "10103": {"rating": "66", "abilities": {"pas": "61", "dri": "73", "phy": "67", "pac": "75", "deff": "30", "sho": "64"}, "Skill-Moves": "4", "Defensive-Workrate": "Med", "club": "heracles-almelo", "age": "20", "Attack-Workrate": "Med", "nation": "61", "potential": "75", "Weak-Foot": "None", "position": "RW", "heigh": "178", "id": "10103", "name": "oussama-tannane"}, "3433": {"rating": "61", "abilities": {"pas": "53", "dri": "59", "phy": "62", "pac": "54", "deff": "35", "sho": "63"}, "Skill-Moves": "2", "Defensive-Workrate": "Med", "club": "heracles-almelo", "age": "25", "Attack-Workrate": "Med", "nation": "31", "potential": "65", "Weak-Foot": "None", "position": "ST", "heigh": "188", "id": "3433", "name": "aleksei-kangaskolkka"}, "11682": {"rating": "62", "abilities": {"pas": "57", "dri": "65", "phy": "39", "pac": "68", "deff": "27", "sho": "59"}, "Skill-Moves": "3", "Defensive-Workrate": "Med", "club": "heracles-almelo", "age": "22", "Attack-Workrate": "Med", "nation": "29", "potential": "66", "Weak-Foot": "None", "position": "RW", "heigh": "175", "id": "11682", "name": "jaroslav-navratil"}, "13488": {"rating": "56", "abilities": {"pas": "49", "dri": "57", "phy": "55", "pac": "61", "deff": "59", "sho": "30"}, "Skill-Moves": "2", "Defensive-Workrate": "Med", "club": "heracles-almelo", "age": "22", "Attack-Workrate": "Med", "nation": "19", "potential": "62", "Weak-Foot": "None", "position": "LB", "heigh": "180", "id": "13488", "name": "mark-engberink"}, "7755": {"rating": "69", "abilities": {"pas": "58", "dri": "72", "phy": "62", "pac": "80", "deff": "40", "sho": "74"}, "Skill-Moves": "3", "Defensive-Workrate": "Med", "club": "heracles-almelo", "age": "23", "Attack-Workrate": "High", "nation": "19", "potential": "72", "Weak-Foot": "None", "position": "LW", "heigh": "170", "id": "7755", "name": "bryan-linssen"}, "8499": {"rating": "66", "abilities": {"pas": "60", "dri": "68", "phy": "68", "pac": "75", "deff": "54", "sho": "61"}, "Skill-Moves": "3", "Defensive-Workrate": "High", "club": "heracles-almelo", "age": "22", "Attack-Workrate": "High", "nation": "19", "potential": "71", "Weak-Foot": "None", "position": "CM", "heigh": "177", "id": "8499", "name": "thomas-bruns"}, "10526": {"rating": "60", "abilities": {"pas": "54", "dri": "65", "phy": "64", "pac": "77", "deff": "57", "sho": "43"}, "Skill-Moves": "2", "Defensive-Workrate": "Low", "club": "heracles-almelo", "age": "21", "Attack-Workrate": "High", "nation": "61", "potential": "67", "Weak-Foot": "None", "position": "LB", "heigh": "182", "id": "10526", "name": "fahd-aktaou"}, "1260": {"rating": "68", "abilities": {"pas": "69", "dri": "65", "phy": "71", "pac": "57", "deff": "57", "sho": "70"}, "Skill-Moves": "2", "Defensive-Workrate": "Med", "club": "heracles-almelo", "age": "31", "Attack-Workrate": "Med", "nation": "19", "potential": "68", "Weak-Foot": "None", "position": "CM", "heigh": "178", "id": "1260", "name": "mark-jan-fledderus"}, "2915": {"rating": "67", "abilities": {"pas": "51", "dri": "59", "phy": "72", "pac": "48", "deff": "35", "sho": "68"}, "Skill-Moves": "2", "Defensive-Workrate": "Med", "club": "heracles-almelo", "age": "26", "Attack-Workrate": "Med", "nation": "20", "potential": "69", "Weak-Foot": "None", "position": "ST", "heigh": "190", "id": "2915", "name": "denni-avdic"}, "8069": {"rating": "68", "abilities": {"pas": "61", "dri": "60", "phy": "71", "pac": "64", "deff": "68", "sho": "46"}, "Skill-Moves": "2", "Defensive-Workrate": "Med", "club": "heracles-almelo", "age": "22", "Attack-Workrate": "Med", "nation": "19", "potential": "73", "Weak-Foot": "None", "position": "RB", "heigh": "191", "id": "8069", "name": "mike-te-wierik"}, "261": {"rating": "65", "abilities": {"pas": "57", "dri": "48", "phy": "74", "pac": "38", "deff": "64", "sho": "48"}, "Skill-Moves": "2", "Defensive-Workrate": "High", "club": "heracles-almelo", "age": "31", "Attack-Workrate": "Med", "nation": "19", "potential": "65", "Weak-Foot": "None", "position": "CDM", "heigh": "183", "id": "261", "name": "bas-sibum"}, "12972": {"rating": "59", "abilities": {"pas": "59", "dri": "55", "phy": "60", "pac": "63", "deff": "40", "sho": "58"}, "Skill-Moves": "1", "Defensive-Workrate": "Med", "club": "heracles-almelo", "age": "21", "Attack-Workrate": "Med", "nation": "19", "potential": "68", "Weak-Foot": "None", "position": "GK", "heigh": "187", "id": "12972", "name": "michael-brouwer"}, "9231": {"rating": "59", "abilities": {"pas": "68", "dri": "55", "phy": "70", "pac": "56", "deff": "31", "sho": "55"}, "Skill-Moves": "1", "Defensive-Workrate": "Med", "club": "heracles-almelo", "age": "21", "Attack-Workrate": "Med", "nation": "19", "potential": "66", "Weak-Foot": "None", "position": "GK", "heigh": "187", "id": "9231", "name": "renze-fij"}, "9232": {"rating": "65", "abilities": {"pas": "53", "dri": "70", "phy": "57", "pac": "88", "deff": "28", "sho": "59"}, "Skill-Moves": "3", "Defensive-Workrate": "Med", "club": "heracles-almelo", "age": "23", "Attack-Workrate": "Med", "nation": "19", "potential": "70", "Weak-Foot": "None", "position": "RW", "heigh": "183", "id": "9232", "name": "edwin-gyasi"}, "15370": {"rating": "62", "abilities": {"pas": "41", "dri": "58", "phy": "73", "pac": "47", "deff": "28", "sho": "64"}, "Skill-Moves": "2", "Defensive-Workrate": "Med", "club": "heracles-almelo", "age": "22", "Attack-Workrate": "Med", "nation": "19", "potential": "67", "Weak-Foot": "None", "position": "ST", "heigh": "197", "id": "15370", "name": "wout-weghorst"}, "6111": {"rating": "65", "abilities": {"pas": "59", "dri": "68", "phy": "65", "pac": "67", "deff": "49", "sho": "62"}, "Skill-Moves": "1", "Defensive-Workrate": "Med", "club": "heracles-almelo", "age": "27", "Attack-Workrate": "Med", "nation": "19", "potential": "67", "Weak-Foot": "None", "position": "GK", "heigh": "192", "id": "6111", "name": "dennis-telgenkamp"}, "10923": {"rating": "62", "abilities": {"pas": "59", "dri": "66", "phy": "56", "pac": "67", "deff": "56", "sho": "53"}, "Skill-Moves": "2", "Defensive-Workrate": "High", "club": "heracles-almelo", "age": "21", "Attack-Workrate": "Med", "nation": "19", "potential": "70", "Weak-Foot": "None", "position": "CM", "heigh": "174", "id": "10923", "name": "menno-heerkes"}, "7425": {"rating": "67", "abilities": {"pas": "59", "dri": "52", "phy": "70", "pac": "61", "deff": "66", "sho": "37"}, "Skill-Moves": "2", "Defensive-Workrate": "Med", "club": "heracles-almelo", "age": "23", "Attack-Workrate": "Med", "nation": "19", "potential": "72", "Weak-Foot": "None", "position": "CB", "heigh": "184", "id": "7425", "name": "bart-schenkeveld"}, "10820": {"rating": "58", "abilities": {"pas": "46", "dri": "41", "phy": "68", "pac": "58", "deff": "54", "sho": "33"}, "Skill-Moves": "2", "Defensive-Workrate": "Med", "club": "heracles-almelo", "age": "20", "Attack-Workrate": "Med", "nation": "19", "potential": "68", "Weak-Foot": "None", "position": "CB", "heigh": "185", "id": "10820", "name": "coen-gortemaker"}, "3501": {"rating": "65", "abilities": {"pas": "55", "dri": "63", "phy": "70", "pac": "66", "deff": "62", "sho": "31"}, "Skill-Moves": "2", "Defensive-Workrate": "Med", "club": "heracles-almelo", "age": "28", "Attack-Workrate": "Med", "nation": "19", "potential": "65", "Weak-Foot": "None", "position": "CB", "heigh": "183", "id": "3501", "name": "milano-koenders"}, "1007": {"rating": "67", "abilities": {"pas": "58", "dri": "56", "phy": "70", "pac": "51", "deff": "65", "sho": "43"}, "Skill-Moves": "2", "Defensive-Workrate": "Med", "club": "heracles-almelo", "age": "31", "Attack-Workrate": "Med", "nation": "19", "potential": "67", "Weak-Foot": "None", "position": "CB", "heigh": "184", "id": "1007", "name": "ramon-zomer"}, "5939": {"rating": "65", "abilities": {"pas": "56", "dri": "45", "phy": "76", "pac": "33", "deff": "64", "sho": "47"}, "Skill-Moves": "2", "Defensive-Workrate": "Med", "club": "heracles-almelo", "age": "25", "Attack-Workrate": "Med", "nation": "19", "potential": "68", "Weak-Foot": "None", "position": "CB", "heigh": "187", "id": "5939", "name": "jeroen-veldmate"}}